src/botstudio/__init__.py
src/botstudio/example.py
botstudio_pip_package-0.0.2.dist-info/METADATA
botstudio_pip_package-0.0.2.dist-info/WHEEL
botstudio_pip_package-0.0.2.dist-info/licenses/LICENSE
botstudio_pip_package-0.0.2.dist-info/RECORD
