Metadata-Version: 2.1
Name: botstudio_pip_package
Version: 0.0.2
Summary: A small example package
Project-URL: Homepage, https://github.com/botstudiotech/pip_package
Project-URL: Bug Tracker, https://github.com/botstudiotech/pip_package/issues
Author-email: Example Author <author@example.com>
License-File: LICENSE
Classifier: License :: OSI Approved :: MIT License
Classifier: Operating System :: OS Independent
Classifier: Programming Language :: Python :: 3
Requires-Python: >=3.7
